sentiment_analysis_lib/__init__.py
sentiment_analysis_lib/sentiment.py
sentiment_analysis_lib-1.1.dist-info/licenses/LICENSE
sentiment_analysis_lib-1.1.dist-info/METADATA
sentiment_analysis_lib-1.1.dist-info/WHEEL
sentiment_analysis_lib-1.1.dist-info/top_level.txt
sentiment_analysis_lib-1.1.dist-info/RECORD
