Metadata-Version: 2.4
Name: sentiment_analysis_lib
Version: 1.1
Summary: This is a simple Python package for analysing sentiment of text data.
Home-page: 
Author: Hemanth
Author-email:  x22183744@student.ncirl.ie
License: MIT
Keywords: sentiment_analysis_lib
Classifier: Intended Audience :: Education
Classifier: Operating System :: Microsoft :: Windows :: Windows 10
Classifier: Programming Language :: Python :: 3
Requires-Python: >=3.6
License-File: LICENSE
Dynamic: author
Dynamic: author-email
Dynamic: classifier
Dynamic: description
Dynamic: keywords
Dynamic: license
Dynamic: license-file
Dynamic: requires-python
Dynamic: summary
